avatarpy/__init__.py
avatarpy/animate.py
avatarpy/annotation.py
avatarpy/avalens.py
avatarpy/avatar.py
avatarpy/core.py
avatarpy/dataset.py
avatarpy/describe.py
avatarpy/transform.py
avatarpy/data/freely_moving.csv
avatarpy/data/freely_moving2.csv
avatarpy-0.1.9.dist-info/LICENSE
avatarpy-0.1.9.dist-info/METADATA
avatarpy-0.1.9.dist-info/WHEEL
avatarpy-0.1.9.dist-info/top_level.txt
avatarpy-0.1.9.dist-info/RECORD
